scopebin/__init__.py
scopebin/io.py
scopebin-0.1.dist-info/LICENSE
scopebin-0.1.dist-info/METADATA
scopebin-0.1.dist-info/WHEEL
scopebin-0.1.dist-info/top_level.txt
scopebin-0.1.dist-info/RECORD
